3-2/CSE 3203/Assignment/verilog/code-and-output/assignment.v
//(~A.B.~C.~D)+(~A.~B.~C.~D)
module assignment(
	input A,
	input B,
	input C,
	input D,
	output z
);

wire A_, B_, C_, D_, p, q, r;
//defining NOTs
not(A_, A);
not(B_, B);
not(C_, C);
not(D_, D);
//defining ANDs
and(p, A_, C_, D_);
and(q, p, B);
and(r, p, B_);
//final result
or(z, q, r);

endmodule

3-2/CSE 3203/Assignment/verilog/code-and-output/stimulus.v
`timescale 1ns / 1ps
module stimulus;

reg A;
reg B;
reg C;
reg D;

wire z;

assignment uut(
	.A(A),
	.B(B),
	.C(C),
	.D(D),
	.z(z)
);

initial begin
	$dumpfile("test.vcd");
	$dumpvars(0, stimulus);
	//0 0 0 0
	A=0;
	B=0;
	C=0;
	D=0;
	#20
	//0 0 0 1
	D=1;
	#20
	//0 0 1 1
	C=1;
	#20
	//0 0 1 0
	D=0;
	#20
	//0 1 1 0
	B=1;
	#20
	//0 1 0 0
	C=0;
	#20
	//1 1 0 0
	A=1;
	#20
	//1 0 0 0
	B=0;
	#20
	//1 0 0 1
	D=1;
	#20
	//1 0 1 1
	C=1;
	#20
	//1 0 1 0
	D=0;
	#20
	//1 1 1 0
	B=1;
	#20
	//1 1 1 1
	D=1;
	#20
	//0 1 1 1
	A=0;
	#20
	//0 1 0 1
	C=0;
	#20
	//1 1 0 1
	A=1;	
	#40;
end

initial begin
	$monitor("A=%d B=%d C=%d D=%d z=%d \n", A, B, C, D, z);
end
endmodule

3-2/CSE 3203/Assignment/verilog/code-and-output/test.vcd
$date
	Sun Nov 29 21:18:46 2020
$end
$version
	Icarus Verilog
$end
$timescale
	1ps
$end
$scope module stimulus $end
$var wire 1 ! z $end
$var reg 1 " A $end
$var reg 1 # B $end
$var reg 1 $ C $end
$var reg 1 % D $end
$scope module uut $end
$var wire 1 " A $end
$var wire 1 & A_ $end
$var wire 1 # B $end
$var wire 1 ' B_ $end
$var wire 1 $ C $end
$var wire 1 ( C_ $end
$var wire 1 % D $end
$var wire 1 ) D_ $end
$var wire 1 * p $end
$var wire 1 + q $end
$var wire 1 , r $end
$var wire 1 ! z $end
$upscope $end
$upscope $end
$enddefinitions $end
#0
$dumpvars
1,
0+
1*
1)
1(
1'
1&
0%
0$
0#
0"
1!
$end
#20000
0!
0,
0*
0)
1%
#40000
0(
1$
#60000
1)
0%
#80000
0'
1#
#100000
1!
1+
1*
1(
0$
#120000
0!
0+
0*
0&
1"
#140000
1'
0#
#160000
0)
1%
#180000
0(
1$
#200000
1)
0%
#220000
0'
1#
#240000
0)
1%
#260000
1&
0"
#280000
1(
0$
#300000
0&
1"
